w2rpy.py
w2rpy-0.3.23.dist-info/licenses/LICENSE
w2rpy-0.3.23.dist-info/METADATA
w2rpy-0.3.23.dist-info/WHEEL
w2rpy-0.3.23.dist-info/top_level.txt
w2rpy-0.3.23.dist-info/RECORD
