Metadata-Version: 2.4
Name: w2rpy
Version: 0.3.23
Summary: Geospatial and Hydraulic Functions For Analysis of River Systems
Author: Luke Russell
Author-email: lrussell@wolfwaterresources.com
License: MIT
License-File: LICENSE
Requires-Dist: pandas
Requires-Dist: openpyxl
Requires-Dist: numpy
Requires-Dist: shapely
Requires-Dist: geopandas
Requires-Dist: rasterio
Requires-Dist: pysheds
Requires-Dist: scipy
Requires-Dist: matplotlib
Dynamic: author
Dynamic: author-email
Dynamic: description
Dynamic: description-content-type
Dynamic: license
Dynamic: license-file
Dynamic: requires-dist
Dynamic: summary
